fb_credentials.py
fb_credentials-0.2.2.dist-info/DESCRIPTION.rst
fb_credentials-0.2.2.dist-info/METADATA
fb_credentials-0.2.2.dist-info/RECORD
fb_credentials-0.2.2.dist-info/WHEEL
fb_credentials-0.2.2.dist-info/metadata.json
fb_credentials-0.2.2.dist-info/top_level.txt
